[
	{
		"INCIDENT_MONTH" : 1,
		"amount" : 8928
	},
	{
		"INCIDENT_MONTH" : 2,
		"amount" : 8598
	},
	{
		"INCIDENT_MONTH" : 3,
		"amount" : 13234
	},
	{
		"INCIDENT_MONTH" : 4,
		"amount" : 19166
	},
	{
		"INCIDENT_MONTH" : 5,
		"amount" : 26518
	},
	{
		"INCIDENT_MONTH" : 6,
		"amount" : 22704
	},
	{
		"INCIDENT_MONTH" : 7,
		"amount" : 34950
	},
	{
		"INCIDENT_MONTH" : 8,
		"amount" : 37395
	},
	{
		"INCIDENT_MONTH" : 9,
		"amount" : 34890
	},
	{
		"INCIDENT_MONTH" : 10,
		"amount" : 32876
	},
	{
		"INCIDENT_MONTH" : 11,
		"amount" : 18141
	},
	{
		"INCIDENT_MONTH" : 12,
		"amount" : 10469
	}
]
